chbpm/__init__.py
chbpm/__main__.py
chbpm/bpm.py
chbpm-0.1.0.dist-info/LICENSE.txt
chbpm-0.1.0.dist-info/METADATA
chbpm-0.1.0.dist-info/WHEEL
chbpm-0.1.0.dist-info/entry_points.txt
chbpm-0.1.0.dist-info/top_level.txt
chbpm-0.1.0.dist-info/RECORD
