Metadata-Version: 2.1
Name: chbpm
Version: 0.1.0
Summary: A Python library for BPM adjustment in audio files
Home-page: https://github.com/dariakriukova/rhythm-is-a-runner.git
Author: Daria Kriukova
Author-email: daria.kriukova@pm.me
Classifier: Programming Language :: Python :: 3
Classifier: License :: OSI Approved :: MIT License
Classifier: Operating System :: OS Independent
License-File: LICENSE.txt
Requires-Dist: librosa
Requires-Dist: pydub
Requires-Dist: soundfile
Requires-Dist: audioread
